pyappsflyer/__init__.py
pyappsflyer/api.py
pyappsflyer/base.py
pyappsflyer/exceptions.py
pyappsflyer/settings.py
pyappsflyer-0.2.dist-info/LICENSE.txt
pyappsflyer-0.2.dist-info/METADATA
pyappsflyer-0.2.dist-info/WHEEL
pyappsflyer-0.2.dist-info/top_level.txt
pyappsflyer-0.2.dist-info/RECORD
