Metadata-Version: 2.1
Name: pyappsflyer
Version: 0.2
Summary: Unofficial python wrap for AppsFlyer API
Home-page: https://github.com/YuriyOrlov/pyappsflyer
Author: Yuriy Orlov
Author-email: navuchodonsr@yandex.ru
License: GPL-3
Platform: UNKNOWN
Requires-Dist: furl (==2.0.0)
Requires-Dist: environs (==4.2.0)
Requires-Dist: requests (==2.22.0)
Requires-Dist: xmltodict (==0.12.0)
Requires-Dist: pytest (==5.3.5)
